LICENSE
MANIFEST.in
README.rst
requirements-test.orig.txt
requirements-test.txt
requirements.orig.txt
requirements.txt
setup.cfg
setup.py
ct_core_db/__init__.py
ct_core_db.egg-info/PKG-INFO
ct_core_db.egg-info/SOURCES.txt
ct_core_db.egg-info/dependency_links.txt
ct_core_db.egg-info/not-zip-safe
ct_core_db.egg-info/requires.txt
ct_core_db.egg-info/top_level.txt
ct_core_db/lib/__init__.py
ct_core_db/lib/association_set.py
ct_core_db/lib/db_utils.py
ct_core_db/lib/mysql_diff.py
ct_core_db/lib/mysql_version.py
ct_core_db/lib/sqla.py
ct_core_db/lib/sqla_types.py