Metadata-Version: 1.1
Name: ct-core-db
Version: 1.2.0
Summary: Catalant Core DB Framework
Home-page: https://github.com/Catalant/ct-core-db
Author: Catalant Technologies
Author-email: engineering@gocatalant.com
License: MIT
Keywords: flask,sqlalchemy,db,database,validation
Platform: UNKNOWN
Classifier: Development Status :: 4 - Beta
Classifier: Intended Audience :: Developers
Classifier: License :: OSI Approved :: MIT License
Classifier: Natural Language :: English
Classifier: Operating System :: OS Independent
Classifier: Programming Language :: Python :: 2 :: Only
Classifier: Programming Language :: SQL
Classifier: Framework :: Flask
Classifier: Topic :: Software Development :: Libraries :: Python Modules
